<resource name="CurrencyService.xsd" isCollection="false" path="/_system/governance/schemas/http/schemas/microsoft/com/2003/10/Serialization/CurrencyService.xsd" registryUrl="https://localhost:9443/registry" md5="c7a79a254f30708f1c7cb108d97aac9d"><mediaType>application/x-xsd+xml</mediaType><version>1796</version><creator>admin</creator><createdTime>1296274618693</createdTime><lastUpdater>admin</lastUpdater><lastModified>1296274618693</lastModified><description></description><properties><property key="targetNamespace">http://schemas.microsoft.com/2003/10/Serialization/</property><property key="registry.artifactId">0c6487c7-ef5f-4eb6-b7ed-a08737695f39</property></properties><associations><association><source>../../../../../../GOTLServices/FaultContracts/2008/01/CurrencyService3.xsd</source><destination>CurrencyService.xsd</destination><type>depends</type></association><association><source>CurrencyService.xsd</source><destination>../../../../../../GOTLServices/FaultContracts/2008/01/CurrencyService3.xsd</destination><type>usedBy</type></association><association><source>../../../../../../www/restfulwebservices/net/DataContracts/2008/01/CurrencyService1.xsd</source><destination>CurrencyService.xsd</destination><type>depends</type></association><association><source>CurrencyService.xsd</source><destination>../../../../../../www/restfulwebservices/net/DataContracts/2008/01/CurrencyService1.xsd</destination><type>usedBy</type></association><association><source>../../../../../../../../wsdls/http/www/restfulwebservices/net/ServiceContracts/2008/01/CurrencyService.svc.wsdl</source><destination>CurrencyService.xsd</destination><type>depends</type></association><association><source>CurrencyService.xsd</source><destination>../../../../../../../../wsdls/http/www/restfulwebservices/net/ServiceContracts/2008/01/CurrencyService.svc.wsdl</destination><type>usedBy</type></association></associations></resource>